{"scoutingData":[{"CompID":"2026week0","MatchID":"q21","DatapointID":"1","ScouterID":"27","TeamID":"4041","AllianceID":"8","DatapointValue":"Outpost","DatapointTimestamp":"0"},{"CompID":"2026week0","MatchID":"q21","DatapointID":"5","ScouterID":"27","TeamID":"4041","AllianceID":"8","DatapointValue":"Blue","DatapointTimestamp":"17"},{"CompID":"2026week0","MatchID":"q21","DatapointID":"11","ScouterID":"27","TeamID":"4041","AllianceID":"8","DatapointValue":"1361","DatapointTimestamp":"3825"},{"CompID":"2026week0","MatchID":"q21","DatapointID":"10","ScouterID":"27","TeamID":"4041","AllianceID":"8","DatapointValue":"1013","DatapointTimestamp":"4374"},{"CompID":"2026week0","MatchID":"q21","DatapointID":"8","ScouterID":"27","TeamID":"4041","AllianceID":"8","DatapointValue":"3157","DatapointTimestamp":"2496"},{"CompID":"2026week0","MatchID":"q21","DatapointID":"7","ScouterID":"27","TeamID":"4041","AllianceID":"8","DatapointValue":"4022","DatapointTimestamp":"1897"},{"CompID":"2026week0","MatchID":"q21","DatapointID":"6","ScouterID":"27","TeamID":"4041","AllianceID":"8","DatapointValue":"5386","DatapointTimestamp":"733"},{"CompID":"2026week0","MatchID":"q21","DatapointID":"9","ScouterID":"27","TeamID":"4041","AllianceID":"8","DatapointValue":"1430","DatapointTimestamp":"6368"},{"CompID":"2026week0","MatchID":"q21","DatapointID":"13","ScouterID":"27","TeamID":"4041","AllianceID":"8","DatapointValue":"true","DatapointTimestamp":"14712"},{"CompID":"2026week0","MatchID":"q21","DatapointID":"14","ScouterID":"27","TeamID":"4041","AllianceID":"8","DatapointValue":"true","DatapointTimestamp":"17545"},{"CompID":"2026week0","MatchID":"q21","DatapointID":"12","ScouterID":"27","TeamID":"4041","AllianceID":"8","DatapointValue":"26–35","DatapointTimestamp":"0"},{"CompID":"2026week0","MatchID":"q21","DatapointID":"17","ScouterID":"27","TeamID":"4041","AllianceID":"8","DatapointValue":"Blue","DatapointTimestamp":"13"},{"CompID":"2026week0","MatchID":"q21","DatapointID":"23","ScouterID":"27","TeamID":"4041","AllianceID":"8","DatapointValue":"6863","DatapointTimestamp":"2909"},{"CompID":"2026week0","MatchID":"q21","DatapointID":"22","ScouterID":"27","TeamID":"4041","AllianceID":"8","DatapointValue":"7252","DatapointTimestamp":"2707"},{"CompID":"2026week0","MatchID":"q21","DatapointID":"18","ScouterID":"27","TeamID":"4041","AllianceID":"8","DatapointValue":"8279","DatapointTimestamp":"1944"},{"CompID":"2026week0","MatchID":"q21","DatapointID":"19","ScouterID":"27","TeamID":"4041","AllianceID":"8","DatapointValue":"8144","DatapointTimestamp":"2279"},{"CompID":"2026week0","MatchID":"q21","DatapointID":"20","ScouterID":"27","TeamID":"4041","AllianceID":"8","DatapointValue":"7464","DatapointTimestamp":"3241"},{"CompID":"2026week0","MatchID":"q21","DatapointID":"24","ScouterID":"27","TeamID":"4041","AllianceID":"8","DatapointValue":"true","DatapointTimestamp":"11519"},{"CompID":"2026week0","MatchID":"q21","DatapointID":"2","ScouterID":"27","TeamID":"4041","AllianceID":"8","DatapointValue":"RED","DatapointTimestamp":"0"},{"CompID":"2026week0","MatchID":"q21","DatapointID":"25","ScouterID":"27","TeamID":"4041","AllianceID":"8","DatapointValue":"L3","DatapointTimestamp":"0"},{"CompID":"2026week0","MatchID":"q21","DatapointID":"26","ScouterID":"27","TeamID":"4041","AllianceID":"8","DatapointValue":"76–100","DatapointTimestamp":"0"},{"CompID":"2026week0","MatchID":"q21","DatapointID":"27","ScouterID":"27","TeamID":"4041","AllianceID":"8","DatapointValue":"80","DatapointTimestamp":"0"},{"CompID":"2026week0","MatchID":"q21","DatapointID":"28","ScouterID":"27","TeamID":"4041","AllianceID":"8","DatapointValue":"10","DatapointTimestamp":"0"}]}